fitvelcurve/__init__.py
fitvelcurve/gal_class.py
fitvelcurve-1.0.0.dist-info/LICENSE
fitvelcurve-1.0.0.dist-info/METADATA
fitvelcurve-1.0.0.dist-info/WHEEL
fitvelcurve-1.0.0.dist-info/top_level.txt
fitvelcurve-1.0.0.dist-info/RECORD
