Metadata-Version: 2.1
Name: fitvelcurve
Version: 1.0.0
License-File: LICENSE
Requires-Dist: numpy ==1.26.4
Requires-Dist: astropy ==6.1.0
Requires-Dist: dynesty ==2.1.3
Requires-Dist: matplotlib ==3.9.0
